lk_banchecker/__init__.py
lk_banchecker-0.1.0.dist-info/licenses/LICENSE
lk_banchecker-0.1.0.dist-info/METADATA
lk_banchecker-0.1.0.dist-info/WHEEL
lk_banchecker-0.1.0.dist-info/top_level.txt
lk_banchecker-0.1.0.dist-info/RECORD
