Metadata-Version: 2.4
Name: lk-banchecker
Version: 0.1.0
Summary: A simple Python wrapper for the lkteam-bancheck API. [MADE BY LK-TEAM]
Author-email: "xPRINCE >> LK-TEAM" <you@example.com>
Project-URL: Homepage, https://unknownbroohahahah
Classifier: Programming Language :: Python :: 3
Classifier: License :: OSI Approved :: MIT License
Classifier: Operating System :: OS Independent
Requires-Python: >=3.7
License-File: LICENSE
Requires-Dist: requests>=2.20.0
Dynamic: license-file
